{
    "key": "group_60b600d188c3b",
    "title": "Layout Settings - Footer",
    "fields": [
        {
            "key": "field_5f8d21eb7b0a0",
            "label": "Footer Settings",
            "name": "",
            "type": "tab",
            "instructions": "",
            "required": 0,
            "conditional_logic": 0,
            "wrapper": {
                "width": "",
                "class": "",
                "id": ""
            },
            "placement": "left",
            "endpoint": 0
        },
        {
            "key": "field_605025fabebf8",
            "label": "Footer Layout Type",
            "name": "footer_layout_type",
            "type": "select",
            "instructions": "",
            "required": 1,
            "conditional_logic": 0,
            "wrapper": {
                "width": "",
                "class": "",
                "id": ""
            },
            "choices": {
                "simple": "Centered Simple Footer",
                "advanced": "Advanced Columns Footer"
            },
            "default_value": "advanced",
            "allow_null": 0,
            "multiple": 0,
            "ui": 0,
            "return_format": "value",
            "ajax": 0,
            "placeholder": ""
        },
        {
            "key": "field_5fb6233b2a722",
            "label": "Show Social Networks Area",
            "name": "show_social_networks_area",
            "type": "true_false",
            "instructions": "Check to display social links in footer",
            "required": 0,
            "conditional_logic": 0,
            "wrapper": {
                "width": "",
                "class": "",
                "id": ""
            },
            "message": "",
            "default_value": 1,
            "ui": 0,
            "ui_on_text": "",
            "ui_off_text": ""
        },
        {
            "key": "field_60500d6e7929a",
            "label": "Footer Columns",
            "name": "footer_columns",
            "type": "number",
            "instructions": "3 or 4 columns in footer, these columns are added in the Widgets area (Appearance)",
            "required": 1,
            "conditional_logic": 0,
            "wrapper": {
                "width": "",
                "class": "",
                "id": ""
            },
            "default_value": 4,
            "placeholder": "",
            "prepend": "",
            "append": "",
            "min": 3,
            "max": 4,
            "step": ""
        },
        {
            "key": "field_605b3329ffff2",
            "label": "Copyright Text",
            "name": "copyright_text",
            "type": "text",
            "instructions": "",
            "required": 1,
            "conditional_logic": 0,
            "wrapper": {
                "width": "",
                "class": "",
                "id": ""
            },
            "default_value": "© Copyright 2021 CATO",
            "placeholder": "",
            "prepend": "",
            "append": "",
            "maxlength": ""
        },
        {
            "key": "field_5fc8a4d5c7daa",
            "label": "Privacy Policy",
            "name": "privacy_policy",
            "type": "text",
            "instructions": "",
            "required": 1,
            "conditional_logic": 0,
            "wrapper": {
                "width": "",
                "class": "",
                "id": ""
            },
            "default_value": "Política de Privacidad",
            "placeholder": "",
            "prepend": "",
            "append": "",
            "maxlength": ""
        },
        {
            "key": "field_5fc8a500c7dab",
            "label": "Privacy Policy URL",
            "name": "privacy_policy_url",
            "type": "page_link",
            "instructions": "",
            "required": 1,
            "conditional_logic": 0,
            "wrapper": {
                "width": "",
                "class": "",
                "id": ""
            },
            "post_type": [
                "page"
            ],
            "taxonomy": "",
            "allow_null": 0,
            "allow_archives": 0,
            "multiple": 0
        },
        {
            "key": "field_5fc8a53fc7dac",
            "label": "Terms and Conditions",
            "name": "terms_and_conditions",
            "type": "text",
            "instructions": "",
            "required": 1,
            "conditional_logic": 0,
            "wrapper": {
                "width": "",
                "class": "",
                "id": ""
            },
            "default_value": "Términos & Condiciones",
            "placeholder": "",
            "prepend": "",
            "append": "",
            "maxlength": ""
        },
        {
            "key": "field_5fc8a562c7dad",
            "label": "Terms and Conditions URL",
            "name": "terms_and_conditions_url",
            "type": "page_link",
            "instructions": "",
            "required": 1,
            "conditional_logic": 0,
            "wrapper": {
                "width": "",
                "class": "",
                "id": ""
            },
            "post_type": [
                "page"
            ],
            "taxonomy": "",
            "allow_null": 0,
            "allow_archives": 0,
            "multiple": 0
        }
    ],
    "location": [
        [
            {
                "param": "options_page",
                "operator": "==",
                "value": "acf-options-footer"
            }
        ]
    ],
    "menu_order": 0,
    "position": "normal",
    "style": "default",
    "label_placement": "top",
    "instruction_placement": "label",
    "hide_on_screen": "",
    "active": true,
    "description": "",
    "modified": 1622681507
}